verilog/dff_veri.v
`timescale 1ns / 1ps

module d_flipflop(D, clk, Q, Qn);
output Q;
output Qn;
input  clk;
input  D;
wire o1,o2,o3,o4 ; 
nand ( o1, D, o2);
nand (o2, clk, o3,o1);
nand (o3, clk, o4);
nand (o4, o3, o1);
nand (Qn, o2, Q);
nand (Q, Qn, o3);

endmodule

verilog/cla.v
module CarryLA_4(a,b,ci,sum,co);

input [3:0] a,b;
input ci; 

output [3:0] sum;
output co;

wire[3:0] g,p,cout;
wire G0,P0;
wire[9:0] w;


// Calculation of Propagate signal Pi
xor x0(p[0],a[0],b[0]);
xor x1(p[1],a[1],b[1]);
xor x2(p[2],a[2],b[2]);
xor x3(p[3],a[3],b[3]);

// Calculation of Generate signal Gi
and a0(g[0],a[0],b[0]); 
and a1(g[1],a[1],b[1]); 
and a2(g[2],a[2],b[2]); 
and a3(g[3],a[3],b[3]); 


and and0(w[0],p[0],ci);
or or0(cout[0],g[0],w[0]);

and and1(w[1],p[1],p[0],ci);
and and2(w[2],p[1],g[0]);
or or1(cout[1],g[1],w[2],w[1]);

and and3(w[3],p[2],p[1],p[0],ci);
and and4(w[4],p[2],p[1],g[0]);
and and5(w[5],p[2],g[1]);
or or2(cout[2],g[2],w[5],w[4],w[3]);

and and6(w[6],p[3],p[2],p[1],g[0]);
and and7(w[7],p[3],p[2],g[1]);
and and8(w[8],p[3],p[2],p[1],p[0],ci);
and and9(w[9],p[3],g[2]);
or or3(cout[3],g[3],w[9],w[8],w[7],w[6]);

and and10(co,cout[3],1);

// Calculation of Sum bits
xor xor0(sum[0],p[0],ci);
xor xor1(sum[1],p[1],cout[0]);
xor xor2(sum[2],p[2],cout[1]);
xor xor3(sum[3],p[3],cout[2]);

endmodule

verilog/cla_tb.v
module CarryLAS_tb;

reg [3:0] a;
reg [3:0] b;
reg cin;
reg clk;
wire [3:0] sumout;
wire [3:0] sumout_ff;
wire [13:0] dum;
wire of; //overflow
wire co;
wire [3:0]input_1;
wire [3:0]input_2;
integer i;


initial	begin
		$dumpfile("CarryLAS_tb.vcd");
		$dumpvars(0,CarryLAS_tb);
	end
   
d_flipflop dff1(a[0],clk,input_1[0], dum[0]);
d_flipflop dff2(b[0],clk,input_2[0], dum[1]);
d_flipflop dff3(a[1],clk,input_1[1], dum[2]);
d_flipflop dff4(b[1],clk,input_2[1], dum[3]);
d_flipflop dff5(a[2],clk,input_1[2], dum[4]);
d_flipflop dff6(b[2],clk,input_2[2], dum[5]);
d_flipflop dff7(a[3],clk,input_1[3], dum[6]);
d_flipflop dff8(b[3],clk,input_2[3], dum[7]);
d_flipflop dff13(cin,clk,ci, dum[12]);


CarryLA_4 CLA(input_1,input_2,ci,sumout,co1);


d_flipflop dff9(sumout[0],clk,sumout_ff[0], dum[8]);
d_flipflop dff10(sumout[1],clk,sumout_ff[1], dum[9]);
d_flipflop dff11(sumout[2],clk,sumout_ff[2], dum[10]);
d_flipflop dff12(sumout[3],clk,sumout_ff[3], dum[11]);
d_flipflop dff14(co1,clk,co, dum[13]);

initial clk = 0;
always #10 clk = ~clk;



initial 
begin
assign cin =0; 
assign a=4'b0101;
assign b=4'b0111;


#20
assign a=4'b1000;
assign b=4'b0111;


#20
assign a=4'b0101;
assign b=4'b0001;
#60
$finish;
end


endmodule

verilog/CarryLAS_tb.vcd
$date
	Thu Apr 29 17:08:55 2021
$end
$version
	Icarus Verilog
$end
$timescale
	1ps
$end
$scope module CarryLAS_tb $end
$var wire 4 ! sumout_ff [3:0] $end
$var wire 4 " sumout [3:0] $end
$var wire 4 # input_2 [3:0] $end
$var wire 4 $ input_1 [3:0] $end
$var wire 14 % dum [13:0] $end
$var wire 1 & co1 $end
$var wire 1 ' co $end
$var wire 1 ( ci $end
$var reg 4 ) a [3:0] $end
$var reg 4 * b [3:0] $end
$var reg 1 + cin $end
$var reg 1 , clk $end
$scope module CLA $end
$var wire 4 - a [3:0] $end
$var wire 4 . b [3:0] $end
$var wire 1 & co $end
$var wire 10 / w [9:0] $end
$var wire 4 0 sum [3:0] $end
$var wire 4 1 p [3:0] $end
$var wire 4 2 g [3:0] $end
$var wire 4 3 cout [3:0] $end
$var wire 1 ( ci $end
$upscope $end
$scope module dff1 $end
$var wire 1 4 D $end
$var wire 1 5 Q $end
$var wire 1 6 Qn $end
$var wire 1 , clk $end
$var wire 1 7 o1 $end
$var wire 1 8 o2 $end
$var wire 1 9 o3 $end
$var wire 1 : o4 $end
$upscope $end
$scope module dff10 $end
$var wire 1 ; D $end
$var wire 1 < Q $end
$var wire 1 = Qn $end
$var wire 1 , clk $end
$var wire 1 > o1 $end
$var wire 1 ? o2 $end
$var wire 1 @ o3 $end
$var wire 1 A o4 $end
$upscope $end
$scope module dff11 $end
$var wire 1 B D $end
$var wire 1 C Q $end
$var wire 1 D Qn $end
$var wire 1 , clk $end
$var wire 1 E o1 $end
$var wire 1 F o2 $end
$var wire 1 G o3 $end
$var wire 1 H o4 $end
$upscope $end
$scope module dff12 $end
$var wire 1 I D $end
$var wire 1 J Q $end
$var wire 1 K Qn $end
$var wire 1 , clk $end
$var wire 1 L o1 $end
$var wire 1 M o2 $end
$var wire 1 N o3 $end
$var wire 1 O o4 $end
$upscope $end
$scope module dff13 $end
$var wire 1 + D $end
$var wire 1 ( Q $end
$var wire 1 P Qn $end
$var wire 1 , clk $end
$var wire 1 Q o1 $end
$var wire 1 R o2 $end
$var wire 1 S o3 $end
$var wire 1 T o4 $end
$upscope $end
$scope module dff14 $end
$var wire 1 & D $end
$var wire 1 ' Q $end
$var wire 1 U Qn $end
$var wire 1 , clk $end
$var wire 1 V o1 $end
$var wire 1 W o2 $end
$var wire 1 X o3 $end
$var wire 1 Y o4 $end
$upscope $end
$scope module dff2 $end
$var wire 1 Z D $end
$var wire 1 [ Q $end
$var wire 1 \ Qn $end
$var wire 1 , clk $end
$var wire 1 ] o1 $end
$var wire 1 ^ o2 $end
$var wire 1 _ o3 $end
$var wire 1 ` o4 $end
$upscope $end
$scope module dff3 $end
$var wire 1 a D $end
$var wire 1 b Q $end
$var wire 1 c Qn $end
$var wire 1 , clk $end
$var wire 1 d o1 $end
$var wire 1 e o2 $end
$var wire 1 f o3 $end
$var wire 1 g o4 $end
$upscope $end
$scope module dff4 $end
$var wire 1 h D $end
$var wire 1 i Q $end
$var wire 1 j Qn $end
$var wire 1 , clk $end
$var wire 1 k o1 $end
$var wire 1 l o2 $end
$var wire 1 m o3 $end
$var wire 1 n o4 $end
$upscope $end
$scope module dff5 $end
$var wire 1 o D $end
$var wire 1 p Q $end
$var wire 1 q Qn $end
$var wire 1 , clk $end
$var wire 1 r o1 $end
$var wire 1 s o2 $end
$var wire 1 t o3 $end
$var wire 1 u o4 $end
$upscope $end
$scope module dff6 $end
$var wire 1 v D $end
$var wire 1 w Q $end
$var wire 1 x Qn $end
$var wire 1 , clk $end
$var wire 1 y o1 $end
$var wire 1 z o2 $end
$var wire 1 { o3 $end
$var wire 1 | o4 $end
$upscope $end
$scope module dff7 $end
$var wire 1 } D $end
$var wire 1 ~ Q $end
$var wire 1 !" Qn $end
$var wire 1 , clk $end
$var wire 1 "" o1 $end
$var wire 1 #" o2 $end
$var wire 1 $" o3 $end
$var wire 1 %" o4 $end
$upscope $end
$scope module dff8 $end
$var wire 1 &" D $end
$var wire 1 '" Q $end
$var wire 1 (" Qn $end
$var wire 1 , clk $end
$var wire 1 )" o1 $end
$var wire 1 *" o2 $end
$var wire 1 +" o3 $end
$var wire 1 ," o4 $end
$upscope $end
$scope module dff9 $end
$var wire 1 -" D $end
$var wire 1 ." Q $end
$var wire 1 /" Qn $end
$var wire 1 , clk $end
$var wire 1 0" o1 $end
$var wire 1 1" o2 $end
$var wire 1 2" o3 $end
$var wire 1 3" o4 $end
$upscope $end
$upscope $end
$enddefinitions $end
#0
$dumpvars
x3"
12"
11"
x0"
x/"
x."
x-"
0,"
1+"
1*"
1)"
x("
x'"
0&"
0%"
1$"
1#"
1""
x!"
x~
0}
1|
1{
1z
0y
xx
xw
1v
1u
1t
1s
0r
xq
xp
1o
1n
1m
1l
0k
xj
xi
1h
0g
1f
1e
1d
xc
xb
0a
1`
1_
1^
0]
x\
x[
1Z
xY
1X
1W
xV
xU
0T
1S
1R
1Q
xP
xO
1N
1M
xL
xK
xJ
xI
xH
1G
1F
xE
xD
xC
xB
xA
1@
1?
x>
x=
x<
x;
1:
19
18
07
x6
x5
14
bx 3
bx 2
bx 1
bx 0
bx /
bx .
bx -
0,
0+
b111 *
b101 )
x(
x'
x&
bx %
bx $
bx #
bx "
bx !
$end
#10000000000000
1V
1B
0&
1>
0;
1I
10"
0-"
b1100 "
b1100 0
b111 3
b100 /
b10 1
b101 2
06
0(
0\
0b
0j
0q
0x
0~
0'"
15
1P
1[
1c
1i
b101 $
b101 -
1p
b111 #
b111 .
1w
1!"
bx1xxxx11000100 %
1("
09
x?
x@
xF
xG
xM
xN
0R
xW
xX
0_
0e
0m
0t
0{
0#"
0*"
x1"
x2"
1,
#20000000000000
1H
1O
1%"
0:
0A
0E
0L
0Y
0u
03"
17
1r
0""
19
1?
1@
1F
1G
1M
1N
1R
1W
1X
1_
1e
1m
1t
1{
1#"
1*"
11"
12"
04
0o
1}
0,
b1000 )
#30000000000000
0&
1;
0E
1-"
1B
0L
b0 3
1I
b0 /
b1111 "
b1111 0
b0 2
b1111 1
05
0<
0D
0K
0'
0p
0!"
0."
16
1=
1C
b1100 !
1J
1U
1q
b1000 $
b1000 -
1~
b11001110010101 %
1/"
08
0?
0G
0N
0R
0W
0_
0e
0m
0s
0{
0$"
0*"
01"
1,
#40000000000000
1A
13"
1:
1u
0>
0n
0|
0%"
00"
1k
1y
07
0r
1""
18
1?
1G
1N
1R
1W
1_
1e
1m
1s
1{
1$"
1*"
11"
0h
0v
14
1o
0}
0,
b1 *
b101 )
#50000000000000
0>
1L
10"
1;
0I
0-"
b110 "
b110 0
b1 3
b100 1
b1 2
06
0=
0i
0q
b1 #
b1 .
0w
0~
0/"
15
1<
1j
b101 $
b101 -
1p
1x
b11000011101100 %
1!"
b1111 !
1."
09
0@
0G
0N
0R
0W
0_
0e
0l
0t
0z
0#"
0*"
02"
1,
#60000000000000
0O
03"
19
1@
1G
1N
1R
1W
1_
1e
1l
1t
1z
1#"
1*"
12"
0,
#70000000000000
0J
b110 !
0."
1K
b11100111101100 %
1/"
09
0@
0G
0M
0R
0W
0_
0e
0l
0t
0z
0#"
0*"
01"
1,
#80000000000000
19
1@
1G
1M
1R
1W
1_
1e
1l
1t
1z
1#"
1*"
11"
0,
#90000000000000
09
0@
0G
0M
0R
0W
0_
0e
0l
0t
0z
0#"
0*"
01"
1,
#100000000000000
19
1@
1G
1M
1R
1W
1_
1e
1l
1t
1z
1#"
1*"
11"
0,
